ci_secrets/__init__.py
ci_secrets/main.py
ci_secrets-1.0.0.dist-info/METADATA
ci_secrets-1.0.0.dist-info/WHEEL
ci_secrets-1.0.0.dist-info/entry_points.txt
ci_secrets-1.0.0.dist-info/top_level.txt
ci_secrets-1.0.0.dist-info/RECORD
